{
  "monday": [
    {
      "id": 1,
      "time": "10:30 AM - 12:30 PM",
      "subject": "SE",
      "sub_code": "3150711",
      "faculty": "AND",
      "type": "Lab",
      "room": "D-205"
    },
    {
      "id": 2,
      "time": "1:00 PM - 2:00 PM",
      "subject": "ADA",
      "sub_code": "3150703",
      "faculty": "JMS",
      "type": "Lecture",
      "room": "D-104"
    },
    {
      "id": 3,
      "time": "2:00 PM - 3:00 PM",
      "subject": "CN",
      "sub_code": "3150710",
      "faculty": "JMR",
      "type": "Lecture",
      "room": "D-104"
    },
    {
      "id": 4,
      "time": "3:15 PM - 4:15 PM",
      "subject": "CN",
      "sub_code": "3150710",
      "faculty": "NRD",
      "type": "Lecture",
      "room": "D-104"
    },
    {
      "id": 5,
      "time": "4:15 PM - 5:15 PM",
      "subject": "PE",
      "sub_code": "3150709",
      "faculty": "NA",
      "type": "Lecture",
      "room": "D-104"
    }
  ],
  "tuesday": [
    {
      "id": 6,
      "time": "10:30 AM - 12:30 PM",
      "subject": "ADA",
      "sub_code": "3150703",
      "faculty": "JMS",
      "type": "Lab",
      "room": "D-204"
    },
    {
      "id": 7,
      "time": "1:00 PM - 2:00 PM",
      "subject": "PDS",
      "sub_code": "3150713",
      "faculty": "BNP",
      "type": "Lecture",
      "room": "D-104"
    },
    {
      "id": 8,
      "time": "2:00 PM - 3:00 PM",
      "subject": "ADA",
      "sub_code": "3150703",
      "faculty": "JMS",
      "type": "Lecture",
      "room": "D-104"
    },
    {
      "id": 9,
      "time": "3:15 PM - 4:15 PM",
      "subject": "PDS",
      "sub_code": "3150713",
      "faculty": "NA",
      "type": "Lecture",
      "room": "D-104"
    },
    {
      "id": 10,
      "time": "4:15 PM - 5:15 PM",
      "subject": "CN",
      "sub_code": "3150710",
      "faculty": "NA",
      "type": "Lecture",
      "room": "D-104"
    }
  ],
  "wednesday": [
    {
      "id": 11,
      "time": "10:30 AM - 12:30 PM",
      "subject": "PDS",
      "sub_code": "3150713",
      "faculty": "BNP",
      "type": "Lab",
      "room": "D-205"
    },
    {
      "id": 12,
      "time": "1:00 PM - 2:00 PM",
      "subject": "SE",
      "sub_code": "3150711",
      "faculty": "AND",
      "type": "Lecture",
      "room": "D-104"
    },
    {
      "id": 13,
      "time": "2:00 PM - 3:00 PM",
      "subject": "CN",
      "sub_code": "3150710",
      "faculty": "JMR",
      "type": "Lecture",
      "room": "D-104"
    },
    {
      "id": 14,
      "time": "3:15 PM - 4:15 PM",
      "subject": "CN",
      "sub_code": "3150710",
      "faculty": "VHB",
      "type": "Lecture",
      "room": "D-104"
    },
    {
      "id": 15,
      "time": "4:15 PM - 5:15 PM",
      "subject": "SE",
      "sub_code": "3150711",
      "faculty": "AND",
      "type": "Lecture",
      "room": "D-104"
    }
  ],
  "thursday": [
    {
      "id": 16,
      "time": "10:30 AM - 12:30 PM",
      "subject": "CN",
      "sub_code": "3150710",
      "faculty": "JMR",
      "type": "Lab",
      "room": "D-205"
    },
    {
      "id": 17,
      "time": "1:00 PM - 2:00 PM",
      "subject": "ADA",
      "sub_code": "3150703",
      "faculty": "RKS",
      "type": "Lecture",
      "room": "D-104"
    },
    {
      "id": 18,
      "time": "2:00 PM - 3:00 PM",
      "subject": "SE",
      "sub_code": "3150711",
      "faculty": "AND",
      "type": "Lecture",
      "room": "D-104"
    },
    {
      "id": 19,
      "time": "3:15 PM - 4:15 PM",
      "subject": "IPDC",
      "sub_code": "3150005",
      "faculty": "NA",
      "type": "Lecture",
      "room": "D-104"
    },
    {
      "id": 20,
      "time": "4:15 PM - 5:15 PM",
      "subject": "IPDC",
      "sub_code": "3150005",
      "faculty": "NA",
      "type": "Lecture",
      "room": "D-104"
    }
  ],
  "friday": [
    {
      "id": 21,
      "time": "10:30 AM - 12:30 PM",
      "subject": "DE-II-B",
      "sub_code": "3150001",
      "faculty":"NA",
      "type": "Lab",
      "room": "D-205"
    },
    {
      "id": 22,
      "time": "1:00 PM - 2:00 PM",
      "subject": "PE",
      "sub_code": "3150709",
      "faculty": "NA",
      "type": "Lecture",
      "room": "D-104"
    },
    {
      "id": 23,
      "time": "2:00 PM - 3:00 PM",
      "subject": "ADA",
      "sub_code": "3150703",
      "faculty": "NA",
      "type": "Lecture",
      "room": "D-104"
    }
  ]
}